zhaws/__init__.py
zhaws/event.py
zhaws/exceptions.py
zhaws/model.py
zhaws/backports/__init__.py
zhaws/backports/enum.py
zhaws/client/__init__.py
zhaws/client/__main__.py
zhaws/client/client.py
zhaws/client/controller.py
zhaws/client/helpers.py
zhaws/client/proxy.py
zhaws/client/model/__init__.py
zhaws/client/model/commands.py
zhaws/client/model/events.py
zhaws/client/model/messages.py
zhaws/client/model/types.py
zhaws/server/__init__.py
zhaws/server/__main__.py
zhaws/server/const.py
zhaws/server/decorators.py
zhaws/server/config/__init__.py
zhaws/server/config/model.py
zhaws/server/config/util.py
zhaws/server/platforms/__init__.py
zhaws/server/platforms/api.py
zhaws/server/platforms/binary_sensor.py
zhaws/server/platforms/device_tracker.py
zhaws/server/platforms/discovery.py
zhaws/server/platforms/helpers.py
zhaws/server/platforms/model.py
zhaws/server/platforms/registries.py
zhaws/server/platforms/sensor.py
zhaws/server/platforms/alarm_control_panel/__init__.py
zhaws/server/platforms/alarm_control_panel/api.py
zhaws/server/platforms/button/__init__.py
zhaws/server/platforms/button/api.py
zhaws/server/platforms/climate/__init__.py
zhaws/server/platforms/climate/api.py
zhaws/server/platforms/cover/__init__.py
zhaws/server/platforms/cover/api.py
zhaws/server/platforms/fan/__init__.py
zhaws/server/platforms/fan/api.py
zhaws/server/platforms/light/__init__.py
zhaws/server/platforms/light/api.py
zhaws/server/platforms/lock/__init__.py
zhaws/server/platforms/lock/api.py
zhaws/server/platforms/number/__init__.py
zhaws/server/platforms/number/api.py
zhaws/server/platforms/select/__init__.py
zhaws/server/platforms/select/api.py
zhaws/server/platforms/siren/__init__.py
zhaws/server/platforms/siren/api.py
zhaws/server/platforms/switch/__init__.py
zhaws/server/platforms/switch/api.py
zhaws/server/platforms/util/__init__.py
zhaws/server/platforms/util/color.py
zhaws/server/util/__init__.py
zhaws/server/websocket/__init__.py
zhaws/server/websocket/client.py
zhaws-2022.2.13.dist-info/LICENSE
zhaws-2022.2.13.dist-info/METADATA
zhaws-2022.2.13.dist-info/WHEEL
zhaws-2022.2.13.dist-info/top_level.txt
zhaws-2022.2.13.dist-info/RECORD
