Metadata-Version: 2.1
Name: zhaws
Version: 2022.2.13
Summary: Library implementing a Zigbee websocket server
Home-page: https://github.com/zigpy/zha-websocket-server
Author: David F. Mulcahey
Author-email: david.mulcahey@icloud.com
License: GPL-3.0
Platform: UNKNOWN
Requires-Dist: colorlog
Requires-Dist: pydantic
Requires-Dist: websockets
Requires-Dist: voluptuous
Requires-Dist: zigpy (==0.43.0)
Requires-Dist: bellows (==0.29.0)
Requires-Dist: zha-quirks (==0.0.66)
Requires-Dist: zigpy-deconz (==0.14.0)
Requires-Dist: zigpy-xbee (==0.14.0)
Requires-Dist: zigpy-zigate (==0.8.0)
Requires-Dist: zigpy-znp (==0.7.0)
Provides-Extra: server
Requires-Dist: uvloop ; extra == 'server'
